README.md
dobuild.py
dostack.py
dotempl.py
doutils.py
setup.cfg
setup.py
dostack.egg-info/PKG-INFO
dostack.egg-info/SOURCES.txt
dostack.egg-info/dependency_links.txt
dostack.egg-info/entry_points.txt
dostack.egg-info/requires.txt
dostack.egg-info/top_level.txt