Metadata-Version: 1.0
Name: dostack
Version: 0.5.4
Summary: A tool to build/help deploy docker containers. Make for docker.
Home-page: UNKNOWN
Author: Rikki Guy @ MHN
Author-email: r.guy@mhnltd.co.uk
License: Copyright MHN Ltd
Keywords: docker build deploy container
Platform: UNKNOWN
